README.rst
setup.py
rtframework/__init__.py
rtframework.egg-info/PKG-INFO
rtframework.egg-info/SOURCES.txt
rtframework.egg-info/dependency_links.txt
rtframework.egg-info/top_level.txt
rtframework/utils/__init__.py
rtframework/utils/filereader.py