Metadata-Version: 1.2
Name: rtframework
Version: 0.0.8
Summary: Test framework geared for stress and load testing
Home-page: https://github.com/Roba-Boba/rtframework
Author: Alex Makasoff
Author-email: alexmakasoff@gmail.com
License: UNKNOWN
Platform: UNKNOWN
Classifier: Programming Language :: Python :: 3
Classifier: License :: OSI Approved :: Apache Software License
Classifier: Operating System :: OS Independent
Requires-Python: >=3.6
